bric_cycling_utilities/__init__.py
bric_cycling_utilities/cycling-utilities.py
bric_cycling_utilities/cycling_utilities.py
bric_cycling_utilities-0.0.1.dist-info/LICENSE
bric_cycling_utilities-0.0.1.dist-info/METADATA
bric_cycling_utilities-0.0.1.dist-info/WHEEL
bric_cycling_utilities-0.0.1.dist-info/top_level.txt
bric_cycling_utilities-0.0.1.dist-info/RECORD
