Metadata-Version: 2.1
Name: bric-cycling-utilities
Version: 0.0.1
Summary: Utilities for cycling stability experiments.
Home-page: UNKNOWN
Author: Brian Carlsen
Author-email: carlsen.bri@gmail.com
License: UNKNOWN
Platform: UNKNOWN
Classifier: Programming Language :: Python :: 3
Classifier: License :: OSI Approved :: MIT License
Classifier: Operating System :: OS Independent
Classifier: Development Status :: 3 - Alpha
